odoo9_addon_base_report_to_printer_mail-9.0.1.0.0-py2.7-nspkg.pth
odoo_addons/base_report_to_printer_mail/__openerp__.py
odoo_addons/base_report_to_printer_mail/__init__.py
odoo_addons/base_report_to_printer_mail/README.rst
odoo_addons/base_report_to_printer_mail/models/mail_template.py
odoo_addons/base_report_to_printer_mail/models/__init__.py
odoo_addons/base_report_to_printer_mail/tests/test_report.py
odoo_addons/base_report_to_printer_mail/tests/__init__.py
odoo9_addon_base_report_to_printer_mail-9.0.1.0.0.dist-info/top_level.txt
odoo9_addon_base_report_to_printer_mail-9.0.1.0.0.dist-info/WHEEL
odoo9_addon_base_report_to_printer_mail-9.0.1.0.0.dist-info/RECORD
odoo9_addon_base_report_to_printer_mail-9.0.1.0.0.dist-info/metadata.json
odoo9_addon_base_report_to_printer_mail-9.0.1.0.0.dist-info/DESCRIPTION.rst
odoo9_addon_base_report_to_printer_mail-9.0.1.0.0.dist-info/METADATA
odoo9_addon_base_report_to_printer_mail-9.0.1.0.0.dist-info/namespace_packages.txt
