Metadata-Version: 2.0
Name: odoo9-addon-base-report-to-printer-mail
Version: 9.0.1.0.0
Summary: Avoid printing a report on email send
Home-page: http://www.Syleam.fr/
Author: SYLEAM, Odoo Community Association (OCA)
Author-email: support@odoo-community.org
License: AGPL-3
Platform: UNKNOWN
Requires-Dist: odoo (<9.1a,>=9.0a)
Requires-Dist: odoo9-addon-base-report-to-printer
Classifier: Programming Language :: Python :: 2.7
Classifier: Framework :: Odoo
Classifier: License :: OSI Approved :: GNU Affero General Public License v3
